agent_synapse-0.2.0.dist-info/licenses/LICENSE
synapse/__init__.py
synapse/agent.py
synapse/agent_loader.py
synapse/cli.py
synapse/dependency_graph.py
synapse/integrations.py
synapse/orchestrator.py
synapse/trace.py
synapse/yaml_loader.py
synapse/dashboard/__init__.py
synapse/dashboard/backend_app.py
agent_synapse-0.2.0.dist-info/METADATA
agent_synapse-0.2.0.dist-info/WHEEL
agent_synapse-0.2.0.dist-info/entry_points.txt
agent_synapse-0.2.0.dist-info/top_level.txt
agent_synapse-0.2.0.dist-info/RECORD
