Metadata-Version: 2.4
Name: agent-synapse
Version: 0.2.0
Summary: Kubernetes-like orchestration system for AI agents
Home-page: https://github.com/YakshithK/synapse
Author: Yakshith Kommineni
Author-email: yakshith.kommineni@gmail.com
Project-URL: Documentation, https://github.com/YakshithK/synapse#readme
Project-URL: Bug Reports, https://github.com/YakshithK/synapse/issues
Project-URL: Source, https://github.com/YakshithK/synapse
Classifier: Development Status :: 3 - Alpha
Classifier: Intended Audience :: Developers
Classifier: License :: OSI Approved :: MIT License
Classifier: Programming Language :: Python :: 3
Classifier: Programming Language :: Python :: 3.8
Classifier: Programming Language :: Python :: 3.9
Classifier: Programming Language :: Python :: 3.10
Classifier: Programming Language :: Python :: 3.11
Requires-Python: >=3.8
License-File: LICENSE
Requires-Dist: typer>=0.9.0
Requires-Dist: pyyaml>=6.0
Requires-Dist: fastapi>=0.100.0
Requires-Dist: uvicorn>=0.23.0
Requires-Dist: jinja2>=3.1.0
Requires-Dist: sqlalchemy>=2.0.0
Requires-Dist: pydantic>=2.0.0
Requires-Dist: rich>=13.0.0
Provides-Extra: dev
Requires-Dist: pytest; extra == "dev"
Requires-Dist: black; extra == "dev"
Requires-Dist: isort; extra == "dev"
Requires-Dist: mypy; extra == "dev"
Requires-Dist: pytest-cov; extra == "dev"
Requires-Dist: pre-commit; extra == "dev"
Dynamic: author
Dynamic: author-email
Dynamic: classifier
Dynamic: description
Dynamic: description-content-type
Dynamic: home-page
Dynamic: license-file
Dynamic: project-url
Dynamic: provides-extra
Dynamic: requires-dist
Dynamic: requires-python
Dynamic: summary
